Openpyxl261ZhongwenWendang/README.md
Openpyxl261ZhongwenWendang/__init__.py
Openpyxl261ZhongwenWendang/__main__.py
Openpyxl261ZhongwenWendang/file.epub
Openpyxl261ZhongwenWendang/index.html
Openpyxl261ZhongwenWendang/css/__init__.py
Openpyxl261ZhongwenWendang/css/annotations.css
Openpyxl261ZhongwenWendang/css/main.css
Openpyxl261ZhongwenWendang/css/normalize.css
Openpyxl261ZhongwenWendang/css/popup.css
Openpyxl261ZhongwenWendang/font/__init__.py
Openpyxl261ZhongwenWendang/font/fontello.eot
Openpyxl261ZhongwenWendang/font/fontello.svg
Openpyxl261ZhongwenWendang/font/fontello.ttf
Openpyxl261ZhongwenWendang/font/fontello.woff
Openpyxl261ZhongwenWendang/img/__init__.py
Openpyxl261ZhongwenWendang/img/annotator-glyph-sprite.png
Openpyxl261ZhongwenWendang/img/annotator-icon-sprite.png
Openpyxl261ZhongwenWendang/img/apple-touch-icon.png
Openpyxl261ZhongwenWendang/img/cancelfullscreen.png
Openpyxl261ZhongwenWendang/img/close.png
Openpyxl261ZhongwenWendang/img/fullscreen.png
Openpyxl261ZhongwenWendang/img/loader.gif
Openpyxl261ZhongwenWendang/img/menu-icon.png
Openpyxl261ZhongwenWendang/img/save.png
Openpyxl261ZhongwenWendang/img/saved.png
Openpyxl261ZhongwenWendang/img/settings-s.png
Openpyxl261ZhongwenWendang/img/settings.png
Openpyxl261ZhongwenWendang/img/star.png
Openpyxl261ZhongwenWendang/js/__init__.py
Openpyxl261ZhongwenWendang/js/epub.js
Openpyxl261ZhongwenWendang/js/epub.min.js
Openpyxl261ZhongwenWendang/js/epub.min.map
Openpyxl261ZhongwenWendang/js/hooks.min.js
Openpyxl261ZhongwenWendang/js/hooks.min.map
Openpyxl261ZhongwenWendang/js/reader.js
Openpyxl261ZhongwenWendang/js/reader.js.map
Openpyxl261ZhongwenWendang/js/reader.min.js
Openpyxl261ZhongwenWendang/js/reader.min.map
Openpyxl261ZhongwenWendang/js/hooks/__init__.py
Openpyxl261ZhongwenWendang/js/hooks/extensions/__init__.py
Openpyxl261ZhongwenWendang/js/hooks/extensions/highlight.js
Openpyxl261ZhongwenWendang/js/libs/__init__.py
Openpyxl261ZhongwenWendang/js/libs/jquery.min.js
openpyxl_2_6_1_zhongwen_wendang-2024.3.5.0.dist-info/METADATA
openpyxl_2_6_1_zhongwen_wendang-2024.3.5.0.dist-info/WHEEL
openpyxl_2_6_1_zhongwen_wendang-2024.3.5.0.dist-info/entry_points.txt
openpyxl_2_6_1_zhongwen_wendang-2024.3.5.0.dist-info/top_level.txt
openpyxl_2_6_1_zhongwen_wendang-2024.3.5.0.dist-info/RECORD
